li_api/__init__.py
li_api/li_topics/__init__.py
li_api/li_topics/pii_analysis_requests/pii_analysis_request_pb2.py
li_api/li_topics/pii_analysis_requests/pii_analysis_request_pb2_grpc.py
li_api-0.1.0.dist-info/WHEEL
li_api-0.1.0.dist-info/METADATA
li_api-0.1.0.dist-info/RECORD
