Metadata-Version: 2.1
Name: li-api
Version: 0.1.0
Summary: 
Author: lex
Author-email: lex@legatoivy.tech
Requires-Python: >=3.8,<4.0
Classifier: Programming Language :: Python :: 3
Classifier: Programming Language :: Python :: 3.10
Classifier: Programming Language :: Python :: 3.8
Classifier: Programming Language :: Python :: 3.9
Requires-Dist: grpcio (==1.29.0)
Requires-Dist: grpcio-tools (==1.29.0)
Requires-Dist: protobuf (==3.12.2)
